{"nodes": [{"id": "d_garage_springaisample_memory_src_main_java_com_example_memory_search_elasticsearchsearchservice_java", "label": "ElasticsearchSearchService.java", "file_type": "code", "source_file": "D:\\Garage\\SpringAISample\\memory\\src\\main\\java\\com\\example\\memory\\search\\ElasticsearchSearchService.java", "source_location": "L1"}, {"id": "search_elasticsearchsearchservice_elasticsearchsearchservice", "label": "ElasticsearchSearchService", "file_type": "code", "source_file": "D:\\Garage\\SpringAISample\\memory\\src\\main\\java\\com\\example\\memory\\search\\ElasticsearchSearchService.java", "source_location": "L21"}, {"id": "search_elasticsearchsearchservice_elasticsearchsearchservice_elasticsearchsearchservice", "label": ".ElasticsearchSearchService()", "file_type": "code", "source_file": "D:\\Garage\\SpringAISample\\memory\\src\\main\\java\\com\\example\\memory\\search\\ElasticsearchSearchService.java", "source_location": "L29"}, {"id": "search_elasticsearchsearchservice_elasticsearchsearchservice_search", "label": ".search()", "file_type": "code", "source_file": "D:\\Garage\\SpringAISample\\memory\\src\\main\\java\\com\\example\\memory\\search\\ElasticsearchSearchService.java", "source_location": "L38"}], "edges": [{"source": "d_garage_springaisample_memory_src_main_java_com_example_memory_search_elasticsearchsearchservice_java", "target": "elasticsearchclient", "relation": "imports", "context": "import", "confidence": "EXTRACTED", "source_file": "D:\\Garage\\SpringAISample\\memory\\src\\main\\java\\com\\example\\memory\\search\\ElasticsearchSearchService.java", "source_location": "L3", "weight": 1.0}, {"source": "d_garage_springaisample_memory_src_main_java_com_example_memory_search_elasticsearchsearchservice_java", "target": "searchresponse", "relation": "imports", "context": "import", "confidence": "EXTRACTED", "source_file": "D:\\Garage\\SpringAISample\\memory\\src\\main\\java\\com\\example\\memory\\search\\ElasticsearchSearchService.java", "source_location": "L4", "weight": 1.0}, {"source": "d_garage_springaisample_memory_src_main_java_com_example_memory_search_elasticsearchsearchservice_java", "target": "hit", "relation": "imports", "context": "import", "confidence": "EXTRACTED", "source_file": "D:\\Garage\\SpringAISample\\memory\\src\\main\\java\\com\\example\\memory\\search\\ElasticsearchSearchService.java", "source_location": "L5", "weight": 1.0}, {"source": "d_garage_springaisample_memory_src_main_java_com_example_memory_search_elasticsearchsearchservice_java", "target": "objectnode", "relation": "imports", "context": "import", "confidence": "EXTRACTED", "source_file": "D:\\Garage\\SpringAISample\\memory\\src\\main\\java\\com\\example\\memory\\search\\ElasticsearchSearchService.java", "source_location": "L6", "weight": 1.0}, {"source": "d_garage_springaisample_memory_src_main_java_com_example_memory_search_elasticsearchsearchservice_java", "target": "logger", "relation": "imports", "context": "import", "confidence": "EXTRACTED", "source_file": "D:\\Garage\\SpringAISample\\memory\\src\\main\\java\\com\\example\\memory\\search\\ElasticsearchSearchService.java", "source_location": "L7", "weight": 1.0}, {"source": "d_garage_springaisample_memory_src_main_java_com_example_memory_search_elasticsearchsearchservice_java", "target": "loggerfactory", "relation": "imports", "context": "import", "confidence": "EXTRACTED", "source_file": "D:\\Garage\\SpringAISample\\memory\\src\\main\\java\\com\\example\\memory\\search\\ElasticsearchSearchService.java", "source_location": "L8", "weight": 1.0}, {"source": "d_garage_springaisample_memory_src_main_java_com_example_memory_search_elasticsearchsearchservice_java", "target": "service", "relation": "imports", "context": "import", "confidence": "EXTRACTED", "source_file": "D:\\Garage\\SpringAISample\\memory\\src\\main\\java\\com\\example\\memory\\search\\ElasticsearchSearchService.java", "source_location": "L9", "weight": 1.0}, {"source": "d_garage_springaisample_memory_src_main_java_com_example_memory_search_elasticsearchsearchservice_java", "target": "ioexception", "relation": "imports", "context": "import", "confidence": "EXTRACTED", "source_file": "D:\\Garage\\SpringAISample\\memory\\src\\main\\java\\com\\example\\memory\\search\\ElasticsearchSearchService.java", "source_location": "L11", "weight": 1.0}, {"source": "d_garage_springaisample_memory_src_main_java_com_example_memory_search_elasticsearchsearchservice_java", "target": "arraylist", "relation": "imports", "context": "import", "confidence": "EXTRACTED", "source_file": "D:\\Garage\\SpringAISample\\memory\\src\\main\\java\\com\\example\\memory\\search\\ElasticsearchSearchService.java", "source_location": "L12", "weight": 1.0}, {"source": "d_garage_springaisample_memory_src_main_java_com_example_memory_search_elasticsearchsearchservice_java", "target": "list", "relation": "imports", "context": "import", "confidence": "EXTRACTED", "source_file": "D:\\Garage\\SpringAISample\\memory\\src\\main\\java\\com\\example\\memory\\search\\ElasticsearchSearchService.java", "source_location": "L13", "weight": 1.0}, {"source": "d_garage_springaisample_memory_src_main_java_com_example_memory_search_elasticsearchsearchservice_java", "target": "map", "relation": "imports", "context": "import", "confidence": "EXTRACTED", "source_file": "D:\\Garage\\SpringAISample\\memory\\src\\main\\java\\com\\example\\memory\\search\\ElasticsearchSearchService.java", "source_location": "L14", "weight": 1.0}, {"source": "d_garage_springaisample_memory_src_main_java_com_example_memory_search_elasticsearchsearchservice_java", "target": "uuid", "relation": "imports", "context": "import", "confidence": "EXTRACTED", "source_file": "D:\\Garage\\SpringAISample\\memory\\src\\main\\java\\com\\example\\memory\\search\\ElasticsearchSearchService.java", "source_location": "L15", "weight": 1.0}, {"source": "d_garage_springaisample_memory_src_main_java_com_example_memory_search_elasticsearchsearchservice_java", "target": "search_elasticsearchsearchservice_elasticsearchsearchservice", "relation": "contains", "confidence": "EXTRACTED", "source_file": "D:\\Garage\\SpringAISample\\memory\\src\\main\\java\\com\\example\\memory\\search\\ElasticsearchSearchService.java", "source_location": "L21", "weight": 1.0}, {"source": "search_elasticsearchsearchservice_elasticsearchsearchservice", "target": "search_elasticsearchsearchservice_elasticsearchsearchservice_elasticsearchsearchservice", "relation": "method", "confidence": "EXTRACTED", "source_file": "D:\\Garage\\SpringAISample\\memory\\src\\main\\java\\com\\example\\memory\\search\\ElasticsearchSearchService.java", "source_location": "L29", "weight": 1.0}, {"source": "search_elasticsearchsearchservice_elasticsearchsearchservice", "target": "search_elasticsearchsearchservice_elasticsearchsearchservice_search", "relation": "method", "confidence": "EXTRACTED", "source_file": "D:\\Garage\\SpringAISample\\memory\\src\\main\\java\\com\\example\\memory\\search\\ElasticsearchSearchService.java", "source_location": "L38", "weight": 1.0}], "raw_calls": [{"caller_nid": "search_elasticsearchsearchservice_elasticsearchsearchservice_search", "callee": "indexName", "is_member_call": false, "source_file": "D:\\Garage\\SpringAISample\\memory\\src\\main\\java\\com\\example\\memory\\search\\ElasticsearchSearchService.java", "source_location": "L39"}, {"caller_nid": "search_elasticsearchsearchservice_elasticsearchsearchservice_search", "callee": "size", "is_member_call": false, "source_file": "D:\\Garage\\SpringAISample\\memory\\src\\main\\java\\com\\example\\memory\\search\\ElasticsearchSearchService.java", "source_location": "L43"}, {"caller_nid": "search_elasticsearchsearchservice_elasticsearchsearchservice_search", "callee": "query", "is_member_call": false, "source_file": "D:\\Garage\\SpringAISample\\memory\\src\\main\\java\\com\\example\\memory\\search\\ElasticsearchSearchService.java", "source_location": "L43"}, {"caller_nid": "search_elasticsearchsearchservice_elasticsearchsearchservice_search", "callee": "index", "is_member_call": false, "source_file": "D:\\Garage\\SpringAISample\\memory\\src\\main\\java\\com\\example\\memory\\search\\ElasticsearchSearchService.java", "source_location": "L43"}, {"caller_nid": "search_elasticsearchsearchservice_elasticsearchsearchservice_search", "callee": "multiMatch", "is_member_call": false, "source_file": "D:\\Garage\\SpringAISample\\memory\\src\\main\\java\\com\\example\\memory\\search\\ElasticsearchSearchService.java", "source_location": "L45"}, {"caller_nid": "search_elasticsearchsearchservice_elasticsearchsearchservice_search", "callee": "fuzziness", "is_member_call": false, "source_file": "D:\\Garage\\SpringAISample\\memory\\src\\main\\java\\com\\example\\memory\\search\\ElasticsearchSearchService.java", "source_location": "L46"}, {"caller_nid": "search_elasticsearchsearchservice_elasticsearchsearchservice_search", "callee": "type", "is_member_call": false, "source_file": "D:\\Garage\\SpringAISample\\memory\\src\\main\\java\\com\\example\\memory\\search\\ElasticsearchSearchService.java", "source_location": "L46"}, {"caller_nid": "search_elasticsearchsearchservice_elasticsearchsearchservice_search", "callee": "fields", "is_member_call": false, "source_file": "D:\\Garage\\SpringAISample\\memory\\src\\main\\java\\com\\example\\memory\\search\\ElasticsearchSearchService.java", "source_location": "L46"}, {"caller_nid": "search_elasticsearchsearchservice_elasticsearchsearchservice_search", "callee": "query", "is_member_call": false, "source_file": "D:\\Garage\\SpringAISample\\memory\\src\\main\\java\\com\\example\\memory\\search\\ElasticsearchSearchService.java", "source_location": "L46"}, {"caller_nid": "search_elasticsearchsearchservice_elasticsearchsearchservice_search", "callee": "hits", "is_member_call": false, "source_file": "D:\\Garage\\SpringAISample\\memory\\src\\main\\java\\com\\example\\memory\\search\\ElasticsearchSearchService.java", "source_location": "L57"}, {"caller_nid": "search_elasticsearchsearchservice_elasticsearchsearchservice_search", "callee": "hits", "is_member_call": false, "source_file": "D:\\Garage\\SpringAISample\\memory\\src\\main\\java\\com\\example\\memory\\search\\ElasticsearchSearchService.java", "source_location": "L57"}, {"caller_nid": "search_elasticsearchsearchservice_elasticsearchsearchservice_search", "callee": "source", "is_member_call": false, "source_file": "D:\\Garage\\SpringAISample\\memory\\src\\main\\java\\com\\example\\memory\\search\\ElasticsearchSearchService.java", "source_location": "L58"}, {"caller_nid": "search_elasticsearchsearchservice_elasticsearchsearchservice_search", "callee": "has", "is_member_call": false, "source_file": "D:\\Garage\\SpringAISample\\memory\\src\\main\\java\\com\\example\\memory\\search\\ElasticsearchSearchService.java", "source_location": "L59"}, {"caller_nid": "search_elasticsearchsearchservice_elasticsearchsearchservice_search", "callee": "source", "is_member_call": false, "source_file": "D:\\Garage\\SpringAISample\\memory\\src\\main\\java\\com\\example\\memory\\search\\ElasticsearchSearchService.java", "source_location": "L59"}, {"caller_nid": "search_elasticsearchsearchservice_elasticsearchsearchservice_search", "callee": "asText", "is_member_call": false, "source_file": "D:\\Garage\\SpringAISample\\memory\\src\\main\\java\\com\\example\\memory\\search\\ElasticsearchSearchService.java", "source_location": "L60"}, {"caller_nid": "search_elasticsearchsearchservice_elasticsearchsearchservice_search", "callee": "get", "is_member_call": false, "source_file": "D:\\Garage\\SpringAISample\\memory\\src\\main\\java\\com\\example\\memory\\search\\ElasticsearchSearchService.java", "source_location": "L60"}, {"caller_nid": "search_elasticsearchsearchservice_elasticsearchsearchservice_search", "callee": "source", "is_member_call": false, "source_file": "D:\\Garage\\SpringAISample\\memory\\src\\main\\java\\com\\example\\memory\\search\\ElasticsearchSearchService.java", "source_location": "L60"}, {"caller_nid": "search_elasticsearchsearchservice_elasticsearchsearchservice_search", "callee": "id", "is_member_call": false, "source_file": "D:\\Garage\\SpringAISample\\memory\\src\\main\\java\\com\\example\\memory\\search\\ElasticsearchSearchService.java", "source_location": "L61"}, {"caller_nid": "search_elasticsearchsearchservice_elasticsearchsearchservice_search", "callee": "score", "is_member_call": false, "source_file": "D:\\Garage\\SpringAISample\\memory\\src\\main\\java\\com\\example\\memory\\search\\ElasticsearchSearchService.java", "source_location": "L62"}, {"caller_nid": "search_elasticsearchsearchservice_elasticsearchsearchservice_search", "callee": "score", "is_member_call": false, "source_file": "D:\\Garage\\SpringAISample\\memory\\src\\main\\java\\com\\example\\memory\\search\\ElasticsearchSearchService.java", "source_location": "L62"}, {"caller_nid": "search_elasticsearchsearchservice_elasticsearchsearchservice_search", "callee": "add", "is_member_call": false, "source_file": "D:\\Garage\\SpringAISample\\memory\\src\\main\\java\\com\\example\\memory\\search\\ElasticsearchSearchService.java", "source_location": "L63"}, {"caller_nid": "search_elasticsearchsearchservice_elasticsearchsearchservice_search", "callee": "warn", "is_member_call": false, "source_file": "D:\\Garage\\SpringAISample\\memory\\src\\main\\java\\com\\example\\memory\\search\\ElasticsearchSearchService.java", "source_location": "L67"}, {"caller_nid": "search_elasticsearchsearchservice_elasticsearchsearchservice_search", "callee": "getMessage", "is_member_call": false, "source_file": "D:\\Garage\\SpringAISample\\memory\\src\\main\\java\\com\\example\\memory\\search\\ElasticsearchSearchService.java", "source_location": "L67"}]}